[
    {
        "许可证状态":"许可证停业到期",
        "姓名":"熊辉",
        "停业到期日期":1744761600000,
        "许可证到期日期":" 2026-11-28",
        "处理状态":"当事人未申请恢复",
        "备注":"未公告"
    },
    {
        "许可证状态":"许可证停业到期",
        "姓名":"董恒涛",
        "停业到期日期":1748822400000,
        "许可证到期日期":1775001600000,
        "处理状态":"当事人未申请恢复",
        "备注":"未公告"
    },
    {
        "许可证状态":"许可证停业到期",
        "姓名":"刘荣军",
        "停业到期日期":1750809600000,
        "许可证到期日期":1826668800000,
        "处理状态":"当事人未申请恢复",
        "备注":"未公告"
    },
    {
        "许可证状态":"许可证停业到期",
        "姓名":"邓红能",
        "停业到期日期":1750896000000,
        "许可证到期日期":1762560000000,
        "处理状态":"当事人未申请恢复",
        "备注":"未公告"
    }
]
